epochflow/__init__.py
epochflow/compiler/__init__.py
epochflow/compiler/ast_compiler.py
epochflow/registry/__init__.py
epochflow/registry/transform_registry.py
epochflow/syntax/__init__.py
epochflow/syntax/rules.py
epochflow/tests/__init__.py
epochflow/tests/test_py_algo_ast_compiler.py
epochflow/tests/py_algo_cases/ambiguous_multi_output/expected.txt
epochflow/tests/py_algo_cases/ambiguous_multi_output/input.txt
epochflow/tests/py_algo_cases/assoc_ops/expected.txt
epochflow/tests/py_algo_cases/assoc_ops/input.txt
epochflow/tests/py_algo_cases/bare_identifier_params/expected.txt
epochflow/tests/py_algo_cases/bare_identifier_params/input.txt
epochflow/tests/py_algo_cases/basic_success/expected.txt
epochflow/tests/py_algo_cases/basic_success/input.txt
epochflow/tests/py_algo_cases/binary_operators/expected.txt
epochflow/tests/py_algo_cases/binary_operators/input.txt
epochflow/tests/py_algo_cases/chained_bool/expected.txt
epochflow/tests/py_algo_cases/chained_bool/input.txt
epochflow/tests/py_algo_cases/deeply_nested_expressions/expected.txt
epochflow/tests/py_algo_cases/deeply_nested_expressions/input.txt
epochflow/tests/py_algo_cases/deferred_tuple_unpacking/expected.txt
epochflow/tests/py_algo_cases/deferred_tuple_unpacking/input.txt
epochflow/tests/py_algo_cases/duplicate_params/expected.txt
epochflow/tests/py_algo_cases/duplicate_params/input.txt
epochflow/tests/py_algo_cases/empty_string_params/expected.txt
epochflow/tests/py_algo_cases/empty_string_params/input.txt
epochflow/tests/py_algo_cases/incompatible_type_cast/expected.txt
epochflow/tests/py_algo_cases/incompatible_type_cast/input.txt
epochflow/tests/py_algo_cases/inline_calls_mixed/expected.txt
epochflow/tests/py_algo_cases/inline_calls_mixed/input.txt
epochflow/tests/py_algo_cases/invalid_attribute_assignment/expected.txt
epochflow/tests/py_algo_cases/invalid_attribute_assignment/input.txt
epochflow/tests/py_algo_cases/invalid_lag_float/expected.txt
epochflow-0.2.0.dist-info/licenses/LICENSE
epochflow-0.2.0.dist-info/METADATA
epochflow-0.2.0.dist-info/WHEEL
epochflow-0.2.0.dist-info/top_level.txt
epochflow-0.2.0.dist-info/RECORD
