Metadata-Version: 2.4
Name: epochflow
Version: 0.2.0
Summary: Algorithm Graph Compiler for DataFlow Execution - Compiles Python-like algorithm specifications into nodes/edges graphs
Author-email: EpochAI Team <support@epochai.com>
Maintainer-email: EpochAI Team <support@epochai.com>
License: MIT
Project-URL: Homepage, https://github.com/epochai/epochflow
Project-URL: Documentation, https://github.com/epochai/epochflow#readme
Project-URL: Repository, https://github.com/epochai/epochflow
Project-URL: Issues, https://github.com/epochai/epochflow/issues
Project-URL: Changelog, https://github.com/epochai/epochflow/releases
Keywords: compiler,ast,dataflow,graph,algorithm,trading,strategy,quantitative,finance
Classifier: Development Status :: 4 - Beta
Classifier: Intended Audience :: Developers
Classifier: Intended Audience :: Financial and Insurance Industry
Classifier: Topic :: Software Development :: Compilers
Classifier: Topic :: Software Development :: Code Generators
Classifier: Topic :: Office/Business :: Financial :: Investment
Classifier: License :: OSI Approved :: MIT License
Classifier: Programming Language :: Python :: 3
Classifier: Programming Language :: Python :: 3.7
Classifier: Programming Language :: Python :: 3.8
Classifier: Programming Language :: Python :: 3.9
Classifier: Programming Language :: Python :: 3.10
Classifier: Programming Language :: Python :: 3.11
Classifier: Programming Language :: Python :: 3.12
Classifier: Operating System :: OS Independent
Classifier: Typing :: Typed
Requires-Python: >=3.7
License-File: LICENSE
Provides-Extra: dev
Requires-Dist: pytest>=7.0.0; extra == "dev"
Requires-Dist: pytest-cov>=4.0.0; extra == "dev"
Requires-Dist: black>=23.0.0; extra == "dev"
Requires-Dist: mypy>=1.0.0; extra == "dev"
Requires-Dist: ruff>=0.1.0; extra == "dev"
Provides-Extra: pandas
Requires-Dist: pandas>=1.3.0; extra == "pandas"
Provides-Extra: all
Requires-Dist: pandas>=1.3.0; extra == "all"
Dynamic: license-file
